{
    "turmas": [
        {
            "id": 1,
            "nome": "Turma A",
            "alunos": [
                {
                    "id": 1,
                    "nome": "Aluno 1",
                    "grupo": 1
                },
                {
                    "id": 2,
                    "nome": "Aluno 2",
                    "grupo": 1
                },
                {
                    "id": 3,
                    "nome": "Aluno 3",
                    "grupo": 1
                },
                {
                    "id": 4,
                    "nome": "Aluno 4",
                    "grupo": null
                },
                {
                    "id": 5,
                    "nome": "Aluno 5",
                    "grupo": null
                }
            ]
        },
        {
            "id": 2,
            "nome": "Turma B",
            "alunos": [
                {
                    "id": 6,
                    "nome": "Aluno 6",
                    "grupo": null
                },
                {
                    "id": 7,
                    "nome": "Aluno 7",
                    "grupo": null
                },
                {
                    "id": 8,
                    "nome": "Aluno 8",
                    "grupo": null
                },
                {
                    "id": 9,
                    "nome": "Aluno 9",
                    "grupo": null
                },
                {
                    "id": 10,
                    "nome": "Aluno 10",
                    "grupo": null
                }
            ],
            "grupos": []
        }
    ]
}
